LICENSE
README.rst
setup.py
SQLExecutorX.egg-info/PKG-INFO
SQLExecutorX.egg-info/SOURCES.txt
SQLExecutorX.egg-info/dependency_links.txt
SQLExecutorX.egg-info/not-zip-safe
SQLExecutorX.egg-info/top_level.txt
sqlexecutorx/__init__.py
sqlexecutorx/_context.py
sqlexecutorx/conf.py
sqlexecutorx/constant.py
sqlexecutorx/core.py
sqlexecutorx/engine.py
sqlexecutorx/error.py
sqlexecutorx/init_import.py
sqlexecutorx/log_support.py
sqlexecutorx/pooling.py
sqlexecutorx/sql_support.py
sqlexecutorx/support.py