Metadata-Version: 2.1
Name: SQLExecutorX
Version: 1.8.6
Summary: A easy、simple thread safe sql executor for Python with connection pool. Support MySQL, PostgreSQL, SQLite etc.
Home-page: https://gitee.com/summry/sqlexecutorx
Author: summy
Author-email: xiazhongbiao@126.com
License: UNKNOWN
Keywords: SQL,MySQL,PostgreSQL,SQLite,Database,Python,RDB
Platform: UNKNOWN
Requires-Python: >=3.6
License-File: LICENSE
